BioAid/Kmers.py
BioAid/__init__.py
BioAid/base.py
BioAid/complexity.py
BioAid/diluter.py
BioAid/popDub.py
BioAid/repeatSearch.py
BioAid/MMBSearchTK/AnnoMMBS.py
BioAid/MMBSearchTK/__init__.py
BioAid/MMBSearchTK/makeMMBSearchRef.py
BioAid/deepSeqInsH/__init__.py
BioAid/deepSeqInsH/annoInsH.py
BioAid/variantTK/__init__.py
BioAid/variantTK/variants.py
bio_aid-0.1.7.dist-info/METADATA
bio_aid-0.1.7.dist-info/WHEEL
bio_aid-0.1.7.dist-info/top_level.txt
bio_aid-0.1.7.dist-info/RECORD
