Metadata-Version: 2.1
Name: bio-aid
Version: 0.1.7
Summary: Genetic Analysis Tools
Home-page: https://github.com/tvarovski/bio-aid
Author: tvarovski (Jerzy Twarowski)
Author-email: <tvarovski1@gmail.com>
License: UNKNOWN
Keywords: python,biology,bio,genetics,genomics,NGS
Platform: UNKNOWN
Classifier: Intended Audience :: Developers
Classifier: Programming Language :: Python :: 3
Classifier: Operating System :: Unix
Classifier: Operating System :: MacOS :: MacOS X
Classifier: Operating System :: Microsoft :: Windows
Requires-Dist: pandas
Requires-Dist: numpy
Requires-Dist: matplotlib
Requires-Dist: seaborn
Requires-Dist: regex
Requires-Dist: pyensembl
Requires-Dist: natsort
Requires-Dist: pysam
